real/__init__.py
real/client.py
pyrealapi-0.0.1.dist-info/METADATA
pyrealapi-0.0.1.dist-info/WHEEL
pyrealapi-0.0.1.dist-info/top_level.txt
pyrealapi-0.0.1.dist-info/RECORD
